gha_utils/__init__.py
gha_utils/__main__.py
gha_utils/binary.py
gha_utils/broken_links.py
gha_utils/bundled_config.py
gha_utils/changelog.py
gha_utils/cli.py
gha_utils/data/__init__.py
gha_utils/data/autofix.yaml
gha_utils/data/autolock.yaml
gha_utils/data/bumpversion.toml
gha_utils/data/changelog.yaml
gha_utils/data/debug.yaml
gha_utils/data/docs.yaml
gha_utils/data/labeller-content-based.yaml
gha_utils/data/labeller-file-based.yaml
gha_utils/data/labels.toml
gha_utils/data/labels.yaml
gha_utils/data/lint.yaml
gha_utils/data/mypy.toml
gha_utils/data/pytest.toml
gha_utils/data/release.yaml
gha_utils/data/renovate.yaml
gha_utils/data/ruff.toml
gha_utils/data/tests.yaml
gha_utils/deps_graph.py
gha_utils/git_ops.py
gha_utils/github.py
gha_utils/lint_repo.py
gha_utils/mailmap.py
gha_utils/matrix.py
gha_utils/metadata.py
gha_utils/py.typed
gha_utils/release_prep.py
gha_utils/renovate.py
gha_utils/sponsor.py
gha_utils/test_plan.py
gha_utils-5.5.1.dist-info/licenses/license
gha_utils-5.5.1.dist-info/WHEEL
gha_utils-5.5.1.dist-info/entry_points.txt
gha_utils-5.5.1.dist-info/METADATA
gha_utils-5.5.1.dist-info/RECORD
