Metadata-Version: 2.4
Name: gha-utils
Version: 5.5.1
Summary: ⚙️ CLI helpers for GitHub Actions + reusable workflows
Keywords: build-automation,changelog-formatter,ci-cd,cli,formatting,github-actions,labels,linting,markdown,mypy,nuitka,packaging,pypi,python,release-automation,sphinx,sponsorship,terminal,typo,workflow-reusable,yaml
Author: Kevin Deldycke
Author-email: Kevin Deldycke <kevin@deldycke.com>
License-Expression: GPL-2.0-or-later
License-File: license
Classifier: Development Status :: 5 - Production/Stable
Classifier: Environment :: Console
Classifier: Framework :: Pelican
Classifier: Framework :: Sphinx
Classifier: Intended Audience :: Developers
Classifier: Operating System :: MacOS :: MacOS X
Classifier: Operating System :: Microsoft :: Windows
Classifier: Operating System :: POSIX :: BSD :: FreeBSD
Classifier: Operating System :: POSIX :: BSD :: NetBSD
Classifier: Operating System :: POSIX :: BSD :: OpenBSD
Classifier: Operating System :: POSIX :: Linux
Classifier: Programming Language :: Python :: 3 :: Only
Classifier: Programming Language :: Python :: 3.10
Classifier: Programming Language :: Python :: 3.11
Classifier: Programming Language :: Python :: 3.12
Classifier: Programming Language :: Python :: 3.13
Classifier: Programming Language :: Python :: 3.14
Classifier: Programming Language :: Python :: Implementation :: CPython
Classifier: Programming Language :: Unix Shell
Classifier: Topic :: Documentation :: Sphinx
Classifier: Topic :: File Formats :: JSON
Classifier: Topic :: Security
Classifier: Topic :: Software Development :: Build Tools
Classifier: Topic :: Software Development :: Compilers
Classifier: Topic :: Software Development :: Documentation
Classifier: Topic :: Software Development :: Libraries :: Python Modules
Classifier: Topic :: Software Development :: Quality Assurance
Classifier: Topic :: Software Development :: Version Control :: Git
Classifier: Topic :: System :: Archiving :: Packaging
Classifier: Topic :: System :: Installation/Setup
Classifier: Topic :: System :: Shells
Classifier: Topic :: System :: Software Distribution
Classifier: Topic :: Terminals
Classifier: Topic :: Text Processing :: Markup :: HTML
Classifier: Topic :: Text Processing :: Markup :: Markdown
Classifier: Topic :: Utilities
Classifier: Typing :: Typed
Requires-Dist: backports-strenum>=1.3.1 ; python_full_version < '3.11'
Requires-Dist: boltons>=25
Requires-Dist: bump-my-version>=1.2.6
Requires-Dist: click-extra>=7
Requires-Dist: extra-platforms>=6
Requires-Dist: packaging>=25
Requires-Dist: py-walk>=0.3.3
Requires-Dist: pydriller>=2.6
Requires-Dist: pyproject-metadata>=0.9
Requires-Dist: pyyaml>=6.0.3
Requires-Dist: tomli>=2.3 ; python_full_version < '3.11'
Requires-Dist: wcmatch>=10
Requires-Python: >=3.10
Project-URL: Changelog, https://github.com/kdeldycke/workflows/blob/main/changelog.md
Project-URL: Download, https://github.com/kdeldycke/workflows/releases/tag/v5.5.1
Project-URL: Funding, https://github.com/sponsors/kdeldycke
Project-URL: Homepage, https://github.com/kdeldycke/workflows
Project-URL: Issues, https://github.com/kdeldycke/workflows/issues
Project-URL: Repository, https://github.com/kdeldycke/workflows
